ambition_rando/__init__.py
ambition_rando/admin.py
ambition_rando/apps.py
ambition_rando/constants.py
ambition_rando/import_from_master.py
ambition_rando/offline_models.py
ambition_rando/randomizer.py
ambition_rando/randomizers.py
ambition_rando/system_checks.py
ambition_rando/urls.py
ambition_rando/utils.py
ambition_rando/view_mixins.py
ambition_rando/management/__init__.py
ambition_rando/management/commands/__init__.py
ambition_rando/management/commands/import_additional.py
ambition_rando/management/commands/import_randomization_list.py
ambition_rando/migrations/0001_initial.py
ambition_rando/migrations/0002_auto_20180706_1519.py
ambition_rando/migrations/0003_auto_20180815_0653.py
ambition_rando/migrations/0004_auto_20181108_0353.py
ambition_rando/migrations/0005_auto_20190305_0123.py
ambition_rando/migrations/0006_auto_20191121_1919.py
ambition_rando/migrations/__init__.py
ambition_rando/models/__init__.py
ambition_rando/models/randomization_list.py
ambition_rando/templates/admin/ambition_rando/change_form.html
ambition_rando/templates/admin/ambition_rando/change_list.html
ambition_rando/tests/__init__.py
ambition_rando/tests/ambition_test_case_mixin.py
ambition_rando/tests/make_test_list.py
ambition_rando/tests/models.py
ambition_rando/tests/test_randomizer.py
ambition_rando-0.1.40.dist-info/AUTHORS
ambition_rando-0.1.40.dist-info/LICENSE
ambition_rando-0.1.40.dist-info/METADATA
ambition_rando-0.1.40.dist-info/WHEEL
ambition_rando-0.1.40.dist-info/top_level.txt
ambition_rando-0.1.40.dist-info/RECORD
