Metadata-Version: 2.1
Name: ambition-rando
Version: 0.1.40
Summary: Randomization class and models for ambition/edc
Home-page: https://github.com/ambition-trial/ambition-rando
Author: Erik van Widenfelt
Author-email: ew2789@gmail.com
License: GPL license, see LICENSE
Keywords: django ambition edc randomization
Platform: UNKNOWN
Classifier: Environment :: Web Environment
Classifier: Framework :: Django
Classifier: Intended Audience :: Developers
Classifier: Intended Audience :: Science/Research
Classifier: License :: OSI Approved :: GNU General Public License v3 (GPLv3)
Classifier: Operating System :: OS Independent
Classifier: Programming Language :: Python :: 3.6
Classifier: Programming Language :: Python :: 3.7
Classifier: Topic :: Internet :: WWW/HTTP
Classifier: Topic :: Internet :: WWW/HTTP :: Dynamic Content
Requires-Python: >=3.7
Requires-Dist: ambition-sites
Requires-Dist: django-crypto-fields
Requires-Dist: django-collect-offline
Requires-Dist: django-collect-offline-files
Requires-Dist: edc-model-admin
Requires-Dist: edc-registration
Requires-Dist: tqdm
